LICENSE.txt
MANIFEST.in
README.md
setup.cfg
setup.py
djangocms_vimeo/__init__.py
djangocms_vimeo/cms_plugins.py
djangocms_vimeo/forms.py
djangocms_vimeo/models.py
djangocms_vimeo/settings.py
djangocms_vimeo/tests.py
djangocms_vimeo.egg-info/PKG-INFO
djangocms_vimeo.egg-info/SOURCES.txt
djangocms_vimeo.egg-info/dependency_links.txt
djangocms_vimeo.egg-info/not-zip-safe
djangocms_vimeo.egg-info/requires.txt
djangocms_vimeo.egg-info/top_level.txt
djangocms_vimeo/migrations/0001_initial.py
djangocms_vimeo/migrations/0002_update_related_name.py
djangocms_vimeo/migrations/__init__.py
djangocms_vimeo/south_migrations/0001_initial.py
djangocms_vimeo/south_migrations/__init__.py
djangocms_vimeo/static/.DS_Store
djangocms_vimeo/static/css/.DS_Store
djangocms_vimeo/static/css/video-js.min.css
djangocms_vimeo/static/css/font/vjs.eot
djangocms_vimeo/static/css/font/vjs.svg
djangocms_vimeo/static/css/font/vjs.ttf
djangocms_vimeo/static/css/font/vjs.woff
djangocms_vimeo/static/js/.DS_Store
djangocms_vimeo/static/js/video.js
djangocms_vimeo/static/js/vjs.vimeo.js
djangocms_vimeo/templates/djangocms_vimeo/video.html
requirements/common.txt
requirements/testing.txt