Metadata-Version: 1.1
Name: djangocms-vimeo
Version: 0.4.0
Summary: Video plugin for django CMS
Home-page: https://github.com/nimbis/djangocms-vimeo
Author: Nimbis Services, Inc.
Author-email: devops@nimbisservices.com
License: LICENSE.txt
Platform: OS Independent
Classifier: Development Status :: 5 - Production/Stable
Classifier: Environment :: Web Environment
Classifier: Framework :: Django
Classifier: Intended Audience :: Developers
Classifier: License :: OSI Approved :: BSD License
Classifier: Operating System :: OS Independent
Classifier: Programming Language :: Python
Classifier: Topic :: Communications
Classifier: Topic :: Internet :: WWW/HTTP :: Dynamic Content
Classifier: Topic :: Internet :: WWW/HTTP :: Dynamic Content :: Message Boards
Classifier: Programming Language :: Python :: 2.6
Classifier: Programming Language :: Python :: 2.7
